prython/__init__.py
prython/__main__.py
prython/prython_src.py
prython-0.0.2.1.dist-info/LICENSE
prython-0.0.2.1.dist-info/METADATA
prython-0.0.2.1.dist-info/WHEEL
prython-0.0.2.1.dist-info/entry_points.txt
prython-0.0.2.1.dist-info/top_level.txt
prython-0.0.2.1.dist-info/RECORD
