Metadata-Version: 2.1
Name: prython
Version: 0.0.2.1
Summary: Runtime microdebugger for Python, inspire by Ruby's pry gem.
Home-page: https://github.com/otamm/Prython
Author: Otavio Ehrenberger
Author-email: ehren.dev.mail@gmail.com
License: MIT
Platform: UNKNOWN
Classifier: License :: OSI Approved :: MIT License
Classifier: Programming Language :: Python :: 2
Classifier: Programming Language :: Python :: 3
Requires-Dist: pathlib ; python_version < "3.4"
